remind/__init__.py
remind/cli.py
remind/consolidation.py
remind/extraction.py
remind/interface.py
remind/mcp_server.py
remind/models.py
remind/retrieval.py
remind/store.py
remind/api/__init__.py
remind/api/routes.py
remind/providers/__init__.py
remind/providers/anthropic.py
remind/providers/azure_openai.py
remind/providers/base.py
remind/providers/ollama.py
remind/providers/openai.py
remind/static/index.html
remind/static/assets/index-BmntGkV9.css
remind/static/assets/index-CnAfM0Fe.js
remind_mcp-0.2.0.dist-info/METADATA
remind_mcp-0.2.0.dist-info/WHEEL
remind_mcp-0.2.0.dist-info/entry_points.txt
remind_mcp-0.2.0.dist-info/licenses/LICENSE
remind_mcp-0.2.0.dist-info/RECORD
