Metadata-Version: 2.4
Name: remind-mcp
Version: 0.2.0
Summary: Generalization-capable memory layer for LLMs with episodic buffers, semantic graphs, and spreading activation retrieval
License-File: LICENSE
Requires-Python: >=3.11
Requires-Dist: anthropic>=0.39.0
Requires-Dist: click>=8.1.0
Requires-Dist: fastmcp>=0.4.0
Requires-Dist: httpx>=0.27.0
Requires-Dist: numpy>=1.26.0
Requires-Dist: openai>=1.52.0
Requires-Dist: python-dotenv>=1.0.0
Requires-Dist: rich>=13.0.0
Requires-Dist: starlette>=0.38.0
Requires-Dist: uvicorn>=0.30.0
Provides-Extra: dev
Requires-Dist: pytest-asyncio>=0.24.0; extra == 'dev'
Requires-Dist: pytest-cov>=4.1.0; extra == 'dev'
Requires-Dist: pytest>=8.0.0; extra == 'dev'
